jupyterlivemagic/__init__.py
jupyterlivemagic/jupyterlivemagic.py
jupyter_live_magic-0.1.2.dist-info/LICENSE.txt
jupyter_live_magic-0.1.2.dist-info/METADATA
jupyter_live_magic-0.1.2.dist-info/WHEEL
jupyter_live_magic-0.1.2.dist-info/top_level.txt
jupyter_live_magic-0.1.2.dist-info/RECORD
