Metadata-Version: 2.1
Name: jupyter-live-magic
Version: 0.1.2
Summary: A Jupyter Notebook %%magic for periodic auto re-run and refresh of Cells
Home-page: https://github.com/srizzo/jupyter-live-magic
Author: Samuel Rizzo
Author-email: rizzolabs@gmail.com
License: MIT
Keywords: ipython,jupyter
Platform: UNKNOWN
Classifier: Intended Audience :: Developers
Classifier: Intended Audience :: System Administrators
Classifier: Intended Audience :: Science/Research
Classifier: Programming Language :: Python
Classifier: Programming Language :: Python :: 2.7
Classifier: Programming Language :: Python :: 3.7
Requires-Dist: jupyter
Requires-Dist: ipywidgets
Requires-Dist: jupyter-interval-widget
